teedoc_plugin_theme_sakurajimamai/__init__.py
teedoc_plugin_theme_sakurajimamai/trans_finish.py
teedoc_plugin_theme_sakurajimamai/trans_prepare.py
teedoc_plugin_theme_sakurajimamai/assets/anchor.svg
teedoc_plugin_theme_sakurajimamai/assets/back.svg
teedoc_plugin_theme_sakurajimamai/assets/dark.css
teedoc_plugin_theme_sakurajimamai/assets/dark_menu.svg
teedoc_plugin_theme_sakurajimamai/assets/dark_mode.svg
teedoc_plugin_theme_sakurajimamai/assets/indicator.svg
teedoc_plugin_theme_sakurajimamai/assets/jquery.min.js
teedoc_plugin_theme_sakurajimamai/assets/light.css
teedoc_plugin_theme_sakurajimamai/assets/light_menu.svg
teedoc_plugin_theme_sakurajimamai/assets/light_mode.svg
teedoc_plugin_theme_sakurajimamai/assets/main.js
teedoc_plugin_theme_sakurajimamai/assets/pre_main.js
teedoc_plugin_theme_sakurajimamai/assets/print.svg
teedoc_plugin_theme_sakurajimamai/assets/prism.min.css
teedoc_plugin_theme_sakurajimamai/assets/prism.min.js
teedoc_plugin_theme_sakurajimamai/assets/split.js
teedoc_plugin_theme_sakurajimamai/assets/to-top.svg
teedoc_plugin_theme_sakurajimamai/assets/tocbot.min.js
teedoc_plugin_theme_sakurajimamai/assets/viewer.min.css
teedoc_plugin_theme_sakurajimamai/assets/viewer.min.js
teedoc_plugin_theme_sakurajimamai/locales/messages.pot
teedoc_plugin_theme_sakurajimamai/locales/ja/LC_MESSAGES/messages.mo
teedoc_plugin_theme_sakurajimamai/locales/ja/LC_MESSAGES/messages.po
teedoc_plugin_theme_sakurajimamai/locales/zh_CN/LC_MESSAGES/messages.mo
teedoc_plugin_theme_sakurajimamai/locales/zh_CN/LC_MESSAGES/messages.po
teedoc_plugin_theme_sakurajimamai/locales/zh_TW/LC_MESSAGES/messages.mo
teedoc_plugin_theme_sakurajimamai/locales/zh_TW/LC_MESSAGES/messages.po
teedoc_plugin_theme_sakurajimamai/templates/404.html
teedoc_plugin_theme_sakurajimamai/templates/article.html
teedoc_plugin_theme_sakurajimamai/templates/page.html
teedoc_plugin_theme_sakurajimamai/templates/page_base.html
teedoc_plugin_theme_sakurajimamai/templates/redirect.html
teedoc_plugin_theme_sakurajimamai-1.0.1.dist-info/LICENSE
teedoc_plugin_theme_sakurajimamai-1.0.1.dist-info/METADATA
teedoc_plugin_theme_sakurajimamai-1.0.1.dist-info/WHEEL
teedoc_plugin_theme_sakurajimamai-1.0.1.dist-info/top_level.txt
teedoc_plugin_theme_sakurajimamai-1.0.1.dist-info/RECORD
